triviapy/__init__.py
triviapy/errors.py
triviapy/game.py
triviapy/question.py
triviapy/urls.py
triviapy/utils.py
aiotriviapy-1.0.dist-info/METADATA
aiotriviapy-1.0.dist-info/WHEEL
aiotriviapy-1.0.dist-info/top_level.txt
aiotriviapy-1.0.dist-info/RECORD
