Metadata-Version: 2.1
Name: aiotriviapy
Version: 1.0
Summary: An aiohttp wrapper for OpenTDB
Home-page: https://github.com/mcurranseijo/triviapy
Author: Keegan Curran
Author-email: mcurranseijo@mail.bradley.edu
License: MIT
Platform: UNKNOWN
Requires-Dist: aiohttp
